[
  {
    "id": "00001",
    "titel": "Geowijzer",
    "schrijver": "Alice Peters & Frans Westerveen",
    "beschrijving": "Hier mist een beschrijving. Deze dient nog geschreven te worden.",
    "vakgebied": "aardrijkskunde",
    "url": "",
    "ob": "visible",
    "mb": "visible",
    "bb": "visible",
    "tags": [""],
    "subcategorie": [""]
  },
  {
    "id": "00002",
    "titel": "Laat maar zien",
    "schrijver": "Jos van Onna & Anky Jacobse",
    "beschrijving": "Hier mist een beschrijving. Deze dient nog geschreven te worden.",
    "vakgebied": "beeldende vorming",
    "url": "",
    "ob": "visible",
    "mb": "visible",
    "bb": "visible",
    "tags": [""],
    "subcategorie": [""]
  },
  {
    "id": "00003",
    "titel": "Bewegingsonderwijs in het speellokaal",
    "schrijver": "T. van den Berg",
    "beschrijving": "Hier mist een beschrijving. Deze dient nog geschreven te worden.",
    "vakgebied": "bewegingsonderwijs",
    "url": "",
    "ob": "visible",
    "mb": "hidden",
    "bb": "hidden",
    "tags": [""],
    "subcategorie": [""]
  },
  {
    "id": "00004",
    "titel": "Kijk op spel",
    "schrijver": "Holger de Nooij",
    "beschrijving": "Hier mist een beschrijving. Deze dient nog geschreven te worden.",
    "vakgebied": "drama",
    "url": "",
    "ob": "visible",
    "mb": "visible",
    "bb": "visible",
    "tags": [""],
    "subcategorie": [""]
  },
  {
    "id": "00005",
    "titel": "Geschiedenis geven: Praktische vakdidatiek voor het basisonderwijs",
    "schrijver": "Meereke Bosua & Ron de Bruin",
    "beschrijving": "Hier mist een beschrijving. Deze dient nog geschreven te worden.",
    "vakgebied": "geschiedenis",
    "url": "",
    "ob": "visible",
    "mb": "visible",
    "bb": "visible",
    "tags": [""],
    "subcategorie": [""]
  },
  {
    "id": "00006",
    "titel": "Werkboek schriftvaardig",
    "schrijver": "Astrid Scholten & Ben Hamerlin",
    "beschrijving": "Hier mist een beschrijving. Deze dient nog geschreven te worden.",
    "vakgebied": "handschrift",
    "url": "",
    "ob": "visible",
    "mb": "visible",
    "bb": "visible",
    "tags": [""],
    "subcategorie": [""]
  },
  {
    "id": "00007",
    "titel": "Schermgaande jeugd",
    "schrijver": "Patti Valkenburg",
    "beschrijving": "Hier mist een beschrijving. Deze dient nog geschreven te worden.",
    "vakgebied": "ict",
    "url": "",
    "ob": "visible",
    "mb": "visible",
    "bb": "visible",
    "tags": [""],
    "subcategorie": [""]
  },
  {
    "id": "00008",
    "titel": "Geloof je het zelf?",
    "schrijver": "Bas van den Berg, Ina ter Avest & Tamar Kopmels",
    "beschrijving": "Hier mist een beschrijving. Deze dient nog geschreven te worden.",
    "vakgebied": "levensbeschouwing",
    "url": "",
    "ob": "visible",
    "mb": "visible",
    "bb": "visible",
    "tags": [""],
    "subcategorie": [""]
  },
  {
    "id": "00009",
    "titel": "Eigen-wijs",
    "schrijver": "Frans Haverkort, Lieuwe Noordam & Rinze van der Lei",
    "beschrijving": "Hier mist een beschrijving. Deze dient nog geschreven te worden.",
    "vakgebied": "muziek",
    "url": "",
    "ob": "visible",
    "mb": "visible",
    "bb": "visible",
    "tags": [""],
    "subcategorie": [""]
  },
  {
    "id": "00010",
    "titel": "Muziek meester!",
    "schrijver": "Frans Haverkort",
    "beschrijving": "Hier mist een beschrijving. Deze dient nog geschreven te worden.",
    "vakgebied": "muziek",
    "url": "",
    "ob": "visible",
    "mb": "visible",
    "bb": "visible",
    "tags": [""],
    "subcategorie": [""]
  },
  {
    "id": "00011",
    "titel": "Natuuronderwijs inzichtelijk",
    "schrijver": "Carla Kersbergen & Amito Haarhuis",
    "beschrijving": "Hier mist een beschrijving. Deze dient nog geschreven te worden.",
    "vakgebied": "natuuronderwijs",
    "url": "",
    "ob": "visible",
    "mb": "visible",
    "bb": "visible",
    "tags": [""],
    "subcategorie": [""]
  },
  {
    "id": "00012",
    "titel": "Praktische didactiek voor natuuronderwijs",
    "schrijver": "Els de Vaan & Jos Marell",
    "beschrijving": "Hier mist een beschrijving. Deze dient nog geschreven te worden.",
    "vakgebied": "natuuronderwijs",
    "url": "",
    "ob": "visible",
    "mb": "visible",
    "bb": "visible",
    "tags": [""],
    "subcategorie": [""]
  },
  {
    "id": "00013",
    "titel": "Cyclisch onderwijs ontwerpen",
    "schrijver": "Anouke Bakx",
    "beschrijving": "Hier mist een beschrijving. Deze dient nog geschreven te worden.",
    "vakgebied": "onderwijskunde pedagogiek",
    "url": "",
    "ob": "visible",
    "mb": "visible",
    "bb": "visible",
    "tags": [""],
    "subcategorie": [""]
  },
  {
    "id": "00014",
    "titel": "Hoe ga je om met kinderen op school en met hun ouders?",
    "schrijver": "Gerda Woltjer & Harry Janssens",
    "beschrijving": "Hier mist een beschrijving. Deze dient nog geschreven te worden.",
    "vakgebied": "onderwijskunde pedagogiek",
    "url": "",
    "ob": "visible",
    "mb": "visible",
    "bb": "visible",
    "tags": [""],
    "subcategorie": [""]
  },
  {
    "id": "00015",
    "titel": "Kiezen voor het jonge kind",
    "schrijver": "Helma Brouwers",
    "beschrijving": "Hier mist een beschrijving. Deze dient nog geschreven te worden.",
    "vakgebied": "onderwijskunde pedagogiek",
    "url": "",
    "ob": "visible",
    "mb": "visible",
    "bb": "hidden",
    "tags": [""],
    "subcategorie": [""]
  },
  {
    "id": "00016",
    "titel": "Ontwikkelingspsychologie",
    "schrijver": "Robert S. Feldman",
    "beschrijving": "Hier mist een beschrijving. Deze dient nog geschreven te worden.",
    "vakgebied": "onderwijskunde pedagogiek",
    "url": "",
    "ob": "visible",
    "mb": "visible",
    "bb": "visible",
    "tags": [""],
    "subcategorie": [""]
  },
  {
    "id": "00017",
    "titel": "Portaal",
    "schrijver": "Harry Paus & Adri van den Brand",
    "beschrijving": "Hier mist een beschrijving. Deze dient nog geschreven te worden.",
    "vakgebied": "taalonderwijs",
    "url": "",
    "ob": "visible",
    "mb": "visible",
    "bb": "visible",
    "tags": [""],
    "subcategorie": [""]
  },
  {
    "id": "00018",
    "titel": "Rekendidactiek: Hele getallen",
    "schrijver": "Petra van den Brom-Snijders, Jos van den Bergh, Ortwin Hutten & Marc van Zanten",
    "beschrijving": "Hier mist een beschrijving. Deze dient nog geschreven te worden.",
    "vakgebied": "rekenen-wiskunde",
    "url": "",
    "ob": "visible",
    "mb": "visible",
    "bb": "visible",
    "tags": [""],
    "subcategorie": ["rw-hele-getallen"]
  },
  {
    "id": "00019",
    "titel": "Rekendidactiek: Meten en meetkunde",
    "schrijver": "Ortwin Hutten, Jos van den Bergh, Petra van den Brom-Snijders & Marc Zanten",
    "beschrijving": "Hier mist een beschrijving. Deze dient nog geschreven te worden.",
    "vakgebied": "rekenen-wiskunde",
    "url": "",
    "ob": "visible",
    "mb": "visible",
    "bb": "visible",
    "tags": [""],
    "subcategorie": ["rw-meten-meetkunde"]
  }
]
